jupyterlab_cfps_preload/__init__.py
jupyterlab_cfps_preload/_version.py
jupyterlab_cfps_preload/labextension/package.json
jupyterlab_cfps_preload/labextension/static/568.aaa999ecae5bb21e9181.js
jupyterlab_cfps_preload/labextension/static/747.d3ecdbd2daa351ab2b15.js
jupyterlab_cfps_preload/labextension/static/remoteEntry.bef79eb319044397ec92.js
jupyterlab_cfps_preload/labextension/static/style.js
jupyterlab_cfps_preload/labextension/static/third-party-licenses.json
jupyterlab_cfps_preload-0.4.0.data/data/share/jupyter/labextensions/jupyterlab_cfps_preload/install.json
jupyterlab_cfps_preload-0.4.0.data/data/share/jupyter/labextensions/jupyterlab_cfps_preload/package.json
jupyterlab_cfps_preload-0.4.0.data/data/share/jupyter/labextensions/jupyterlab_cfps_preload/static/568.aaa999ecae5bb21e9181.js
jupyterlab_cfps_preload-0.4.0.data/data/share/jupyter/labextensions/jupyterlab_cfps_preload/static/747.d3ecdbd2daa351ab2b15.js
jupyterlab_cfps_preload-0.4.0.data/data/share/jupyter/labextensions/jupyterlab_cfps_preload/static/remoteEntry.bef79eb319044397ec92.js
jupyterlab_cfps_preload-0.4.0.data/data/share/jupyter/labextensions/jupyterlab_cfps_preload/static/style.js
jupyterlab_cfps_preload-0.4.0.data/data/share/jupyter/labextensions/jupyterlab_cfps_preload/static/third-party-licenses.json
jupyterlab_cfps_preload-0.4.0.dist-info/LICENSE
jupyterlab_cfps_preload-0.4.0.dist-info/METADATA
jupyterlab_cfps_preload-0.4.0.dist-info/WHEEL
jupyterlab_cfps_preload-0.4.0.dist-info/top_level.txt
jupyterlab_cfps_preload-0.4.0.dist-info/RECORD
