Metadata-Version: 2.1
Name: jupyterlab-cfps-preload
Version: 0.4.0
Summary: Load necessary files into Jupyter Lab
Home-page: https://github.com/lie-flat/cfps-jupyterhub/tree/master/jupyterlab_cfps_preload
Author: kxxt
Author-email: rsworktech@outlook.com
License: BSD-3-Clause
Keywords: Jupyter,JupyterLab,JupyterLab3
Platform: Linux
Platform: Mac OS X
Platform: Windows
Classifier: License :: OSI Approved :: BSD License
Classifier: Programming Language :: Python
Classifier: Programming Language :: Python :: 3
Classifier: Programming Language :: Python :: 3.6
Classifier: Programming Language :: Python :: 3.7
Classifier: Programming Language :: Python :: 3.8
Classifier: Programming Language :: Python :: 3.9
Classifier: Programming Language :: Python :: 3.10
Classifier: Framework :: Jupyter
Classifier: Framework :: Jupyter :: JupyterLab
Classifier: Framework :: Jupyter :: JupyterLab :: 3
Classifier: Framework :: Jupyter :: JupyterLab :: Extensions
Classifier: Framework :: Jupyter :: JupyterLab :: Extensions :: Prebuilt
Requires-Python: >=3.6
License-File: LICENSE
Requires-Dist: jupyterlab (~=3.0)
